planaieditor/__init__.py
planaieditor/app.py
planaieditor/codesnippets/debug_monitor.py
planaieditor/codesnippets/export_clean.py
planaieditor/codesnippets/export_execute.py
planaieditor/codesnippets/inspect_module.py
planaieditor/codesnippets/releasenotes.py
planaieditor/filesystem.py
planaieditor/llm_interface_utils.py
planaieditor/lsp_handler.py
planaieditor/patch.py
planaieditor/python.py
planaieditor/socket_server.py
planaieditor/static_frontend/_app/env.js
planaieditor/static_frontend/_app/immutable/assets/0.Ca45FmGi.css
planaieditor/static_frontend/_app/immutable/assets/2.DwZ1WPOt.css
planaieditor/static_frontend/_app/immutable/assets/JSONC.tmLanguage.DGdrviQG.json
planaieditor/static_frontend/_app/immutable/assets/MagicPython.tmLanguage.DSrfAYO2.json
planaieditor/static_frontend/_app/immutable/assets/MagicRegExp.tmLanguage.XKSD9R-M.json
planaieditor/static_frontend/_app/immutable/assets/_layout.xwbjdxxR.css
planaieditor/static_frontend/_app/immutable/assets/_page.CPG7zwQn.css
planaieditor/static_frontend/_app/immutable/assets/codicon.Bwdt_oQx.ttf
planaieditor/static_frontend/_app/immutable/assets/dark_modern.B9RTFwxS.json
planaieditor/static_frontend/_app/immutable/assets/dark_vs.BL-mUvcK.json
planaieditor/static_frontend/_app/immutable/assets/editor.Bu8Q8M8w.css
planaieditor/static_frontend/_app/immutable/assets/hc_black.BX9MT4w9.json
planaieditor/static_frontend/_app/immutable/assets/hc_light.Bzw0ew6e.json
planaieditor/static_frontend/_app/immutable/assets/index.CUV9KVs8.css
planaieditor/static_frontend/_app/immutable/assets/inspectEditorTokens.BPOe4Pu5.css
planaieditor/static_frontend/_app/immutable/assets/light_modern.3YkGE-nX.json
planaieditor/static_frontend/_app/immutable/assets/light_vs.DwwM7VRG.json
planaieditor/static_frontend/_app/immutable/assets/monaco.0E5kpWi1.css
planaieditor/static_frontend/_app/immutable/assets/onig.Du5pRr7Y.wasm
planaieditor/static_frontend/_app/immutable/assets/snippets.tmLanguage.Bt1Bw9n-.json
planaieditor-0.2.dist-info/METADATA
planaieditor-0.2.dist-info/WHEEL
planaieditor-0.2.dist-info/entry_points.txt
planaieditor-0.2.dist-info/RECORD
