Metadata-Version: 2.3
Name: planaieditor
Version: 0.2
Summary: PlanAI Editor Backend and UI Server
License: Apache-2.0
Author: Niels Provos
Author-email: niels@provos.com
Requires-Python: >=3.10,<4.0
Classifier: License :: OSI Approved :: Apache Software License
Classifier: Programming Language :: Python :: 3
Classifier: Programming Language :: Python :: 3.10
Classifier: Programming Language :: Python :: 3.11
Classifier: Programming Language :: Python :: 3.12
Classifier: Programming Language :: Python :: 3.13
Requires-Dist: black (>=25.1.0,<26.0.0)
Requires-Dist: eventlet (>=0.39.1,<0.40.0)
Requires-Dist: flask (>=3.1.0,<4.0.0)
Requires-Dist: flask-cors (>=5.0.1) ; python_version >= "3.10" and python_version < "4.0"
Requires-Dist: flask-socketio (>=5.5.1,<6.0.0)
Requires-Dist: isort (>=6.0.1,<7.0.0)
Requires-Dist: jedi-language-server (>=0.45.1,<0.46.0)
Requires-Dist: llm-interface (>=0.1.11,<0.2.0)
Requires-Dist: planai[all] (>=0.6.0) ; python_version >= "3.10" and python_version < "4.0"
